Metadata-Version: 2.1
Name: polyatomic_complexes
Version: 1.0.8
License-File: LICENSE
Requires-Dist: ase>=3.24.0
Requires-Dist: babel>=2.16.0
Requires-Dist: beautifulsoup4>=4.12.3
Requires-Dist: biopandas>=0.5.1
Requires-Dist: biopython>=1.84
Requires-Dist: bioservices>=1.11.2
Requires-Dist: botorch>=0.12.0
Requires-Dist: cpdb-protein>=0.2.0
Requires-Dist: dftd3>=1.2.1
Requires-Dist: dill>=0.3.9
Requires-Dist: gauche>=0.1.6
Requires-Dist: geometric>=1.0.2
Requires-Dist: git-lfs>=1.6
Requires-Dist: gpytorch>=1.13
Requires-Dist: GraKeL>=0.1.10
Requires-Dist: graphein>=1.7.7
Requires-Dist: gudhi>=3.10.1
Requires-Dist: jax>=0.4.38
Requires-Dist: jaxlib>=0.4.38
Requires-Dist: matplotlib>=3.10.0
Requires-Dist: monty>=2025.1.9
Requires-Dist: mpmath>=1.3.0
Requires-Dist: networkx>=3.4.2
Requires-Dist: numpy>=1.26.4
Requires-Dist: pandas
Requires-Dist: periodictable>=2.0.2
Requires-Dist: pillow>=11.1.0
Requires-Dist: plotly>=5.24.1
Requires-Dist: pymatgen>=2025.1.9
Requires-Dist: pyro-api>=0.1.2
Requires-Dist: pyro-ppl>=1.9.1
Requires-Dist: pyscf>=2.8.0
Requires-Dist: rdkit>=2024.9.4
Requires-Dist: scikit-learn>=1.6.1
Requires-Dist: scipy>=1.15.0
Requires-Dist: seaborn>=0.13.2
Requires-Dist: selfies>=2.1.2
Requires-Dist: sympy>=1.13.1
Requires-Dist: TopoNetX>=0.2.0
Requires-Dist: torch>=2.5.1
